st_file_browser/__init__.py
st_file_browser/frontend/build/asset-manifest.json
st_file_browser/frontend/build/bootstrap.min.css
st_file_browser/frontend/build/index.html
st_file_browser/frontend/build/precache-manifest.a0596225e23638cb17232461d8504d40.js
st_file_browser/frontend/build/service-worker.js
st_file_browser/frontend/build/static/css/2.5a3919a9.chunk.css
st_file_browser/frontend/build/static/css/2.5a3919a9.chunk.css.map
st_file_browser/frontend/build/static/js/2.0e6934a9.chunk.js
st_file_browser/frontend/build/static/js/2.0e6934a9.chunk.js.LICENSE.txt
st_file_browser/frontend/build/static/js/2.0e6934a9.chunk.js.map
st_file_browser/frontend/build/static/js/main.4551d177.chunk.js
st_file_browser/frontend/build/static/js/main.4551d177.chunk.js.map
st_file_browser/frontend/build/static/js/runtime-main.5606d314.js
st_file_browser/frontend/build/static/js/runtime-main.5606d314.js.map
st_file_browser/frontend/build/static/media/fontawesome-webfont.674f50d2.eot
st_file_browser/frontend/build/static/media/fontawesome-webfont.912ec66d.svg
st_file_browser/frontend/build/static/media/fontawesome-webfont.af7ae505.woff2
st_file_browser/frontend/build/static/media/fontawesome-webfont.b06871f2.ttf
st_file_browser/frontend/build/static/media/fontawesome-webfont.fee66e71.woff
st_file_browser-0.1.1.dist-info/METADATA
st_file_browser-0.1.1.dist-info/WHEEL
st_file_browser-0.1.1.dist-info/top_level.txt
st_file_browser-0.1.1.dist-info/RECORD
