Metadata-Version: 2.1
Name: st-file-browser
Version: 0.1.1
Summary: A streamlit file browser
Home-page: https://github.com/hoggatt/st-file-browser
Author: hoggatt
Author-email: 
Project-URL: Source Code, https://github.com/hoggatt/st-file-browser
Requires-Python: >=3.6
Requires-Dist: wcmatch
Requires-Dist: streamlit >=1.0
